fares/__init__.py
fares/subscription_offering.py
fares/dimension/__init__.py
fares/dimension/dimension.py
tests/__init__.py
tests/test_cluster_applicability.py
tests/test_subscription_offering.py
fares_rule_engine-0.0.15.dist-info/METADATA
fares_rule_engine-0.0.15.dist-info/WHEEL
fares_rule_engine-0.0.15.dist-info/top_level.txt
fares_rule_engine-0.0.15.dist-info/RECORD
